dash_react_simple_maps/DashReactSimpleMaps.py
dash_react_simple_maps/__init__.py
dash_react_simple_maps/_imports_.py
dash_react_simple_maps/constants.py
dash_react_simple_maps/dash_react_simple_maps.min.js
dash_react_simple_maps/dash_react_simple_maps.min.js.map
dash_react_simple_maps/metadata.json
dash_react_simple_maps/package-info.json
dash_react_simple_maps-0.0.2.dist-info/LICENSE
dash_react_simple_maps-0.0.2.dist-info/METADATA
dash_react_simple_maps-0.0.2.dist-info/WHEEL
dash_react_simple_maps-0.0.2.dist-info/top_level.txt
dash_react_simple_maps-0.0.2.dist-info/RECORD
