Metadata-Version: 2.1
Name: dash_react_simple_maps
Version: 0.0.2
Summary: react-simple-maps for Dash
Author: Ploomber Inc. <contact@ploomber.io>
License: Apache-2.0
Classifier: Framework :: Dash
License-File: LICENSE
